netviewer/__init__.py
netviewer/__main__.py
netviewer/config.py
netviewer/context.py
netviewer/ip/__init__.py
netviewer/ip/bridge.py
netviewer/ip/inet.py
netviewer/ip/interface.py
netviewer/ip/link.py
netviewer/ip/link_info.py
netviewer/ip/link_info_bond.py
netviewer/ip/link_info_bridge.py
netviewer/ip/link_info_bridge_slave.py
netviewer/ip/link_info_tunnel.py
netviewer/ip/link_info_veth.py
netviewer/ip/route.py
netviewer/model/__init__.py
netviewer/model/bridge.py
netviewer/model/inet.py
netviewer/model/interface.py
netviewer/model/link.py
netviewer/model/link_info.py
netviewer/model/link_info_bond.py
netviewer/model/link_info_bridge.py
netviewer/model/link_info_bridge_slave.py
netviewer/model/link_info_tunnel.py
netviewer/model/link_info_veth.py
netviewer/model/route.py
netviewer/py.typed
netviewer/types.py
netviewer/utils.py
netviewer/view/__init__.py
netviewer/view/color.py
netviewer/view/console.py
netviewer/view/filter.py
netviewer/view/render/__init__.py
netviewer/view/render/bridge.py
netviewer/view/render/interface.py
netviewer/view/render/link.py
netviewer/view/render/link_info.py
netviewer/view/render/link_info_bond.py
netviewer/view/render/link_info_bridge.py
netviewer/view/render/link_info_bridge_slave.py
netviewer/view/render/link_info_tunnel.py
netviewer/view/render/link_info_veth.py
netviewer/view/render/route.py
netviewer/view/render/utils.py
netviewer/view/theme.py
netviewer/view/visibility.py
netviewer-0.1.0.dist-info/entry_points.txt
netviewer-0.1.0.dist-info/WHEEL
netviewer-0.1.0.dist-info/METADATA
netviewer-0.1.0.dist-info/RECORD
